adaflow/__init__.py
adaflow/av/__init__.py
adaflow/av/utils.py
adaflow/av/data/__init__.py
adaflow/av/data/av_data_frame.py
adaflow/av/data/av_data_packet.py
adaflow/av/metadata/__init__.py
adaflow/av/metadata/flow_json_meta.py
adaflow/av/pipeline/__init__.py
adaflow/av/pipeline/pipeline_composer.py
adaflow/av/pipeline/pipeline_factory.py
adaflow/av/pipeline/dialects/__init__.py
adaflow/av/pipeline/dialects/base_pipeline.py
adaflow/av/pipeline/dialects/delegate_gstreamer_pipeline.py
adaflow/av/pipeline/dialects/dialect_template_helper.py
adaflow/av/pipeline/dialects/duplex_gstreamer_pipeline.py
adaflow/av/pipeline/dialects/gst_context.py
adaflow/av/pipeline/dialects/gst_tools.py
adaflow/av/pipeline/dialects/gstreamer_pipeline.py
adaflow/av/pipeline/dialects/readable_gstreamer_pipeline.py
adaflow/av/pipeline/dialects/writable_gstreamer_pipeline.py
adaflow/av/pipeline/model/__init__.py
adaflow/av/pipeline/model/attribute.py
adaflow/av/pipeline/model/graph.py
adaflow/av/pipeline/model/struct.py
adaflow/cli/__init__.py
adaflow/cli/base.py
adaflow/cli/cli.py
adaflow/cli/init.py
adaflow/cli/launch.py
adaflow-0.0.1.dist-info/LICENSE
adaflow-0.0.1.dist-info/METADATA
adaflow-0.0.1.dist-info/WHEEL
adaflow-0.0.1.dist-info/entry_points.txt
adaflow-0.0.1.dist-info/top_level.txt
adaflow-0.0.1.dist-info/RECORD
