Metadata-Version: 2.1
Name: adaflow
Version: 0.0.1
Summary: AdaFlow is a multimedia pipeline frameworks to offer Deep Learning model integration.
Home-page: https://github.com/modelscope/adaflow
Author: "long.qul, jingyao.ww, jiayong.djy, hanbing.han, yulin.yu"
License: MIT License
Keywords: example,setuptools
Classifier: License :: OSI Approved :: BSD License
Classifier: Programming Language :: Python :: 3
Requires-Python: >=3.7
License-File: LICENSE
Requires-Dist: numpy
Requires-Dist: matplotlib
Requires-Dist: networkx
Requires-Dist: PyGObject
Requires-Dist: jinja2
Requires-Dist: jsonschema
Requires-Dist: pyyaml
